{"annotations":{"list":[{"builtIn":1,"datasource":{"type":"grafana","uid":"-- Grafana --"},"enable":true,"hide":true,"iconColor":"rgba(0, 211, 255, 1)","name":"Annotations & Alerts","type":"dashboard"}]},"editable":true,"fiscalYearStartMonth":0,"graphTooltip":0,"id":29,"links":[],"panels":[{"datasource":{"type":"prometheus","uid":"prometheus"},"fieldConfig":{"defaults":{"color":{"mode":"continuous-RdYlGr"},"mappings":[{"options":{"0":{"color":"yellow","index":1,"text":"DOWN"},"1":{"color":"green","index":0,"text":"UP"}},"type":"value"},{"options":{"match":"null+nan","result":{"color":"red","index":2,"text":"DOWN"}},"type":"special"}],"noValue":"NO VALUE","thresholds":{"mode":"absolute","steps":[{"color":"green","value":null},{"color":"red","value":80}]}},"overrides":[]},"gridPos":{"h":8,"w":12,"x":0,"y":0},"id":1,"options":{"displayMode":"lcd","maxVizHeight":300,"minVizHeight":16,"minVizWidth":8,"namePlacement":"auto","orientation":"horizontal","reduceOptions":{"calcs":["lastNotNull"],"fields":"","values":false},"showUnfilled":true,"sizing":"auto","valueMode":"color"},"pluginVersion":"10.4.1","targets":[{"datasource":{"type":"prometheus","uid":"prometheus"},"editorMode":"code","expr":"tempo_build_info","instant":true,"legendFormat":"tempo-{{container}}","range":true,"refId":"A"},{"datasource":{"type":"prometheus","uid":"prometheus"},"editorMode":"code","expr":"prometheus_build_info","hide":false,"instant":false,"legendFormat":"{{container}}","range":true,"refId":"B"},{"datasource":{"type":"prometheus","uid":"prometheus"},"editorMode":"code","expr":"grafana_build_info","hide":false,"instant":false,"legendFormat":"{{ container }}","range":true,"refId":"C"}],"title":"Availability Observability","type":"bargauge"},{"datasource":{"type":"prometheus","uid":"prometheus"},"fieldConfig":{"defaults":{"color":{"mode":"continuous-RdYlGr"},"mappings":[{"options":{"0":{"color":"yellow","index":1,"text":"DOWN"},"1":{"color":"green","index":0,"text":"UP"}},"type":"value"},{"options":{"match":"null+nan","result":{"color":"red","index":2,"text":"DOWN"}},"type":"special"}],"noValue":"NO VALUE","thresholds":{"mode":"absolute","steps":[{"color":"green","value":null},{"color":"red","value":80}]}},"overrides":[]},"gridPos":{"h":8,"w":12,"x":12,"y":0},"id":3,"options":{"displayMode":"lcd","maxVizHeight":300,"minVizHeight":16,"minVizWidth":8,"namePlacement":"auto","orientation":"horizontal","reduceOptions":{"calcs":["lastNotNull"],"fields":"","values":false},"showUnfilled":true,"sizing":"auto","valueMode":"color"},"pluginVersion":"10.4.1","targets":[{"datasource":{"type":"prometheus","uid":"prometheus"},"editorMode":"code","expr":"probe_success","hide":false,"instant":false,"legendFormat":"{{ target }}","range":true,"refId":"C"}],"title":"Availability Services","type":"bargauge"},{"datasource":{"type":"prometheus","uid":"prometheus"},"fieldConfig":{"defaults":{"color":{"mode":"palette-classic"},"custom":{"axisBorderShow":false,"axisCenteredZero":false,"axisColorMode":"text","axisLabel":"","axisPlacement":"auto","barAlignment":0,"drawStyle":"line","fillOpacity":25,"gradientMode":"none","hideFrom":{"legend":false,"tooltip":false,"viz":false},"insertNulls":false,"lineInterpolation":"linear","lineWidth":1,"pointSize":5,"scaleDistribution":{"type":"linear"},"showPoints":"auto","spanNulls":false,"stacking":{"group":"A","mode":"normal"},"thresholdsStyle":{"mode":"off"}},"mappings":[],"thresholds":{"mode":"absolute","steps":[{"color":"green","value":null},{"color":"red","value":80}]}},"overrides":[]},"gridPos":{"h":8,"w":12,"x":0,"y":8},"id":2,"options":{"legend":{"calcs":[],"displayMode":"hidden","placement":"right","showLegend":false},"tooltip":{"mode":"single","sort":"none"}},"targets":[{"datasource":{"type":"prometheus","uid":"prometheus"},"editorMode":"code","expr":"tempo_distributor_spans_received_total","hide":false,"instant":false,"legendFormat":"__auto","range":true,"refId":"B"},{"datasource":{"type":"prometheus","uid":"prometheus"},"editorMode":"code","expr":"tempo_receiver_accepted_spans","instant":false,"legendFormat":"{{__name__}}","range":true,"refId":"A"},{"datasource":{"type":"prometheus","uid":"prometheus"},"editorMode":"code","expr":"tempo_receiver_refused_spans","hide":false,"instant":false,"legendFormat":"{{__name__}}","range":true,"refId":"C"}],"title":"Received spans","type":"timeseries"}],"refresh":"10s","schemaVersion":39,"tags":[],"templating":{"list":[]},"time":{"from":"now-15m","to":"now"},"timepicker":{},"timezone":"browser","title":"Observability","uid":"adkjewyl0hjb4f","version":5,"weekStart":""}